django_time_logs/__init__.py
django_time_logs/admin.py
django_time_logs/apps.py
django_time_logs/middleware.py
django_time_logs/models.py
django_time_logs/serializers.py
django_time_logs/tests.py
django_time_logs/urls.py
django_time_logs/utils.py
django_time_logs/views.py
django_time_logs/templates/django_time_logs/time_logs.html
django_time_logs-0.1.0.dist-info/METADATA
django_time_logs-0.1.0.dist-info/WHEEL
django_time_logs-0.1.0.dist-info/top_level.txt
django_time_logs-0.1.0.dist-info/RECORD
