Metadata-Version: 2.4
Name: django-time-logs
Version: 0.1.0
Summary: A simple Django application that helps you track the execution time of functions, class views, and middleware ( with elasticsearch optional for logging)
Author-email: Fatai Ogundele <ogundele.fatai.k@gmail.com>
License: MIT
Project-URL: Homepage, https://github.com/Fattyk/django-time-logs
Project-URL: Issues, https://github.com/Fattyk/django-time-logs/issues
Classifier: Development Status :: 3 - Alpha
Classifier: Environment :: Web Environment
Classifier: Framework :: Django
Classifier: Intended Audience :: Developers
Classifier: License :: OSI Approved :: MIT License
Classifier: Programming Language :: Python :: 3
Classifier: Programming Language :: Python :: 3.8
Classifier: Programming Language :: Python :: 3.9
Requires-Python: >=3.8
Requires-Dist: Django>=3.2
Requires-Dist: elasticsearch-dsl>=7.0.0
